cal/__init__.py
cal/maxdrawback.py
seeking_odds_cal-0.1.0.dist-info/METADATA
seeking_odds_cal-0.1.0.dist-info/WHEEL
seeking_odds_cal-0.1.0.dist-info/top_level.txt
seeking_odds_cal-0.1.0.dist-info/RECORD
